		{
			"type1": [
				{
					"idx": 0
				},
				{
					"idx": 1,
					"name": "윤성로",
					"doctorField": "신부전, 당뇨병/고혈압성 신질환, 투석, 신장이식, 사구체신염",
					"career": [
						"가톨릭 중앙의료원 부속병원 인턴",
						"가톨릭 중앙의료원 부속병원 레지던트",
						"1992.4 ~ 1994.4국군수도통합병원 내과장",
						"1995.5 ~ 1996.2강남성모병원 내과 신장학 교실 임상강사",
						"1996.3 ~ 2000.1가톨릭의대 내과학 교실 전임강사",
						"건양대학교병원 교육연구부장 역임"
					],
					"morning": {
						"mon": "",
						"tue": "진료",
						"wen": "진료",
						"thr": "",
						"fir": "",
						"sat": "2주"
					},
					"afternoon": {
						"mon": "",
						"tue": "진료",
						"wen": "",
						"thr": "",
						"fir": "",
						"sat": "진료"
					},
					"other": {
						"first": "출장 : 2023-02-13~2023-02-14",
						"second": "출장 : 2023-02-15~2023-02-15"
					},
					"doctorImg": "윤성로_교수"
				},
				{
					"idx": 2,
					"name": "황원민",
					"doctorField": "혈뇨, 단백뇨, 부종, 만성신부전, 투석, 신장이식, 노인의학",
					"career": [
						"대전광역시 의사회 부회장",
						"EBS 명의 스페셜",
						"건양대학교병원 심사평가실장 역임",
						"현) 건양대학교병원 심사평가실장"
					],
					"morning": {
						"mon": "진료",
						"tue": "",
						"wen": "진료",
						"thr": "",
						"fir": "",
						"sat": "2주"
					},
					"afternoon": {
						"mon": "",
						"tue": "진료",
						"wen": "",
						"thr": "진료",
						"fir": "",
						"sat": "진료"
					},
					"other": {
						"first": "출장 : 2023-02-13~2023-02-14",
						"second": "출장 : 2023-02-15~2023-02-15"
					},
					"doctorImg": "황원민_교수"
				},
				{
					"idx": 3,
					"name": "윤세희",
					"doctorField": "혈뇨, 단백뇨, 부종, 만성신부전, 투석, 신장이식, 노인의학",
					"career": [
						"대전광역시 의사회 부회장",
						"EBS 명의 스페셜",
						"건양대학교병원 심사평가실장 역임",
						"현) 건양대학교병원 심사평가실장"
					],
					"morning": {
						"mon": "진료",
						"tue": "",
						"wen": "진료",
						"thr": "",
						"fir": "",
						"sat": "2주"
					},
					"afternoon": {
						"mon": "",
						"tue": "진료",
						"wen": "",
						"thr": "진료",
						"fir": "",
						"sat": "진료"
					},
					"other": {
						"first": "출장 : 2023-02-13~2023-02-14",
						"second": "출장 : 2023-02-15~2023-02-15"
					},
					"doctorImg": "윤세희_교수"
				},
				{
					"idx": 4,
					"name": "박요한",
					"doctorField": "혈뇨, 단백뇨, 부종, 만성신부전, 투석, 신장이식, 노인의학",
					"career": [
						"대전광역시 의사회 부회장",
						"EBS 명의 스페셜",
						"건양대학교병원 심사평가실장 역임",
						"현) 건양대학교병원 심사평가실장"
					],
					"morning": {
						"mon": "진료",
						"tue": "",
						"wen": "진료",
						"thr": "",
						"fir": "",
						"sat": "2주"
					},
					"afternoon": {
						"mon": "",
						"tue": "진료",
						"wen": "",
						"thr": "진료",
						"fir": "",
						"sat": "진료"
					},
					"other": {
						"first": "출장 : 2023-02-13~2023-02-14",
						"second": "출장 : 2023-02-15~2023-02-15"
					},
					"doctorImg": "박요한_교수"
				},
				{
					"idx": 5,
					"name": "박성지",
					"doctorField": "혈뇨, 단백뇨, 부종, 만성신부전, 투석, 신장이식, 노인의학",
					"career": [
						"대전광역시 의사회 부회장",
						"EBS 명의 스페셜",
						"건양대학교병원 심사평가실장 역임",
						"현) 건양대학교병원 심사평가실장"
					],
					"morning": {
						"mon": "진료",
						"tue": "",
						"wen": "진료",
						"thr": "",
						"fir": "",
						"sat": "2주"
					},
					"afternoon": {
						"mon": "",
						"tue": "진료",
						"wen": "",
						"thr": "진료",
						"fir": "",
						"sat": "진료"
					},
					"other": {
						"first": "출장 : 2023-02-13~2023-02-14",
						"second": "출장 : 2023-02-15~2023-02-15"
					},
					"doctorImg": "박성지_교수"
				}
			],
			"type2": [
				{
					"idx": 0
				},
				{
					"idx": 1,
					"name": "윤성로",
					"doctorField": "신부전, 당뇨병/고혈압성 신질환, 투석, 신장이식, 사구체신염",
					"career": [
						"가톨릭 중앙의료원 부속병원 인턴",
						"가톨릭 중앙의료원 부속병원 레지던트",
						"1992.4 ~ 1994.4국군수도통합병원 내과장",
						"1995.5 ~ 1996.2강남성모병원 내과 신장학 교실 임상강사",
						"1996.3 ~ 2000.1가톨릭의대 내과학 교실 전임강사",
						"건양대학교병원 교육연구부장 역임"
					],
					"morning": {
						"mon": "",
						"tue": "진료",
						"wen": "진료",
						"thr": "",
						"fir": "",
						"sat": "2주"
					},
					"afternoon": {
						"mon": "",
						"tue": "진료",
						"wen": "",
						"thr": "",
						"fir": "",
						"sat": "진료"
					},
					"other": {
						"first": "출장 : 2023-02-13~2023-02-14",
						"second": "출장 : 2023-02-15~2023-02-15"
					},
					"doctorImg": "윤성로_교수"
				},
				{
					"idx": 2,
					"name": "황원민",
					"doctorField": "혈뇨, 단백뇨, 부종, 만성신부전, 투석, 신장이식, 노인의학",
					"career": [
						"대전광역시 의사회 부회장",
						"EBS 명의 스페셜",
						"건양대학교병원 심사평가실장 역임",
						"현) 건양대학교병원 심사평가실장"
					],
					"morning": {
						"mon": "진료",
						"tue": "",
						"wen": "진료",
						"thr": "",
						"fir": "",
						"sat": "2주"
					},
					"afternoon": {
						"mon": "",
						"tue": "진료",
						"wen": "",
						"thr": "진료",
						"fir": "",
						"sat": "진료"
					},
					"other": {
						"first": "출장 : 2023-02-13~2023-02-14",
						"second": "출장 : 2023-02-15~2023-02-15"
					},
					"doctorImg": "황원민_교수"
				},
				{
					"idx": 3,
					"name": "윤세희",
					"doctorField": "혈뇨, 단백뇨, 부종, 만성신부전, 투석, 신장이식, 노인의학",
					"career": [
						"대전광역시 의사회 부회장",
						"EBS 명의 스페셜",
						"건양대학교병원 심사평가실장 역임",
						"현) 건양대학교병원 심사평가실장"
					],
					"morning": {
						"mon": "진료",
						"tue": "",
						"wen": "진료",
						"thr": "",
						"fir": "",
						"sat": "2주"
					},
					"afternoon": {
						"mon": "",
						"tue": "진료",
						"wen": "",
						"thr": "진료",
						"fir": "",
						"sat": "진료"
					},
					"other": {
						"first": "출장 : 2023-02-13~2023-02-14",
						"second": "출장 : 2023-02-15~2023-02-15"
					},
					"doctorImg": "윤세희_교수"
				},
				{
					"idx": 4,
					"name": "박요한",
					"doctorField": "혈뇨, 단백뇨, 부종, 만성신부전, 투석, 신장이식, 노인의학",
					"career": [
						"대전광역시 의사회 부회장",
						"EBS 명의 스페셜",
						"건양대학교병원 심사평가실장 역임",
						"현) 건양대학교병원 심사평가실장"
					],
					"morning": {
						"mon": "진료",
						"tue": "",
						"wen": "진료",
						"thr": "",
						"fir": "",
						"sat": "2주"
					},
					"afternoon": {
						"mon": "",
						"tue": "진료",
						"wen": "",
						"thr": "진료",
						"fir": "",
						"sat": "진료"
					},
					"other": {
						"first": "출장 : 2023-02-13~2023-02-14",
						"second": "출장 : 2023-02-15~2023-02-15"
					},
					"doctorImg": "박요한_교수"
				},
				{
					"idx": 5,
					"name": "박성지",
					"doctorField": "혈뇨, 단백뇨, 부종, 만성신부전, 투석, 신장이식, 노인의학",
					"career": [
						"대전광역시 의사회 부회장",
						"EBS 명의 스페셜",
						"건양대학교병원 심사평가실장 역임",
						"현) 건양대학교병원 심사평가실장"
					],
					"morning": {
						"mon": "진료",
						"tue": "",
						"wen": "진료",
						"thr": "",
						"fir": "",
						"sat": "2주"
					},
					"afternoon": {
						"mon": "",
						"tue": "진료",
						"wen": "",
						"thr": "진료",
						"fir": "",
						"sat": "진료"
					},
					"other": {
						"first": "출장 : 2023-02-13~2023-02-14",
						"second": "출장 : 2023-02-15~2023-02-15"
					},
					"doctorImg": "박성지_교수"
				}
			],
			"type3": [
				{
					"idx": 0
				},
				{
					"idx": 1,
					"name": "김현우",
					"doctorField": "신부전, 당뇨병/고혈압성 신질환, 투석, 신장이식, 사구체신염",
					"career": [
						"가톨릭 중앙의료원 부속병원 인턴",
						"가톨릭 중앙의료원 부속병원 레지던트",
						"1992.4 ~ 1994.4국군수도통합병원 내과장",
						"1995.5 ~ 1996.2강남성모병원 내과 신장학 교실 임상강사",
						"1996.3 ~ 2000.1가톨릭의대 내과학 교실 전임강사",
						"건양대학교병원 교육연구부장 역임"
					],
					"morning": {
						"mon": "",
						"tue": "진료",
						"wen": "진료",
						"thr": "",
						"fir": "",
						"sat": "2주"
					},
					"afternoon": {
						"mon": "",
						"tue": "진료",
						"wen": "",
						"thr": "",
						"fir": "",
						"sat": "진료"
					},
					"other": {
						"first": "출장 : 2023-02-13~2023-02-14",
						"second": "출장 : 2023-02-15~2023-02-15"
					},
					"doctorImg": "윤성로_교수"
				},
				{
					"idx": 2,
					"name": "신의규",
					"doctorField": "혈뇨, 단백뇨, 부종, 만성신부전, 투석, 신장이식, 노인의학",
					"career": [
						"대전광역시 의사회 부회장",
						"EBS 명의 스페셜",
						"건양대학교병원 심사평가실장 역임",
						"현) 건양대학교병원 심사평가실장"
					],
					"morning": {
						"mon": "진료",
						"tue": "",
						"wen": "진료",
						"thr": "",
						"fir": "",
						"sat": "2주"
					},
					"afternoon": {
						"mon": "",
						"tue": "진료",
						"wen": "",
						"thr": "진료",
						"fir": "",
						"sat": "진료"
					},
					"other": {
						"first": "출장 : 2023-02-13~2023-02-14",
						"second": "출장 : 2023-02-15~2023-02-15"
					},
					"doctorImg": "황원민_교수"
				}
			],
			"type4": [
				{
					"idx": 0
				},
				{
					"idx": 1,
					"name": "김현우",
					"doctorField": "신부전, 당뇨병/고혈압성 신질환, 투석, 신장이식, 사구체신염",
					"career": [
						"가톨릭 중앙의료원 부속병원 인턴",
						"가톨릭 중앙의료원 부속병원 레지던트",
						"1992.4 ~ 1994.4국군수도통합병원 내과장",
						"1995.5 ~ 1996.2강남성모병원 내과 신장학 교실 임상강사",
						"1996.3 ~ 2000.1가톨릭의대 내과학 교실 전임강사",
						"건양대학교병원 교육연구부장 역임"
					],
					"morning": {
						"mon": "",
						"tue": "진료",
						"wen": "진료",
						"thr": "",
						"fir": "",
						"sat": "2주"
					},
					"afternoon": {
						"mon": "",
						"tue": "진료",
						"wen": "",
						"thr": "",
						"fir": "",
						"sat": "진료"
					},
					"other": {
						"first": "출장 : 2023-02-13~2023-02-14",
						"second": "출장 : 2023-02-15~2023-02-15"
					},
					"doctorImg": "윤성로_교수"
				},
				{
					"idx": 2,
					"name": "신의규",
					"doctorField": "혈뇨, 단백뇨, 부종, 만성신부전, 투석, 신장이식, 노인의학",
					"career": [
						"대전광역시 의사회 부회장",
						"EBS 명의 스페셜",
						"건양대학교병원 심사평가실장 역임",
						"현) 건양대학교병원 심사평가실장"
					],
					"morning": {
						"mon": "진료",
						"tue": "",
						"wen": "진료",
						"thr": "",
						"fir": "",
						"sat": "2주"
					},
					"afternoon": {
						"mon": "",
						"tue": "진료",
						"wen": "",
						"thr": "진료",
						"fir": "",
						"sat": "진료"
					},
					"other": {
						"first": "출장 : 2023-02-13~2023-02-14",
						"second": "출장 : 2023-02-15~2023-02-15"
					},
					"doctorImg": "황원민_교수"
				}
			],
			"type5": [
				{
					"idx": 0
				},
				{
					"idx": 1,
					"name": "김현우",
					"doctorField": "신부전, 당뇨병/고혈압성 신질환, 투석, 신장이식, 사구체신염",
					"career": [
						"가톨릭 중앙의료원 부속병원 인턴",
						"가톨릭 중앙의료원 부속병원 레지던트",
						"1992.4 ~ 1994.4국군수도통합병원 내과장",
						"1995.5 ~ 1996.2강남성모병원 내과 신장학 교실 임상강사",
						"1996.3 ~ 2000.1가톨릭의대 내과학 교실 전임강사",
						"건양대학교병원 교육연구부장 역임"
					],
					"morning": {
						"mon": "",
						"tue": "진료",
						"wen": "진료",
						"thr": "",
						"fir": "",
						"sat": "2주"
					},
					"afternoon": {
						"mon": "",
						"tue": "진료",
						"wen": "",
						"thr": "",
						"fir": "",
						"sat": "진료"
					},
					"other": {
						"first": "출장 : 2023-02-13~2023-02-14",
						"second": "출장 : 2023-02-15~2023-02-15"
					},
					"doctorImg": "윤성로_교수"
				},
				{
					"idx": 2,
					"name": "신의규",
					"doctorField": "혈뇨, 단백뇨, 부종, 만성신부전, 투석, 신장이식, 노인의학",
					"career": [
						"대전광역시 의사회 부회장",
						"EBS 명의 스페셜",
						"건양대학교병원 심사평가실장 역임",
						"현) 건양대학교병원 심사평가실장"
					],
					"morning": {
						"mon": "진료",
						"tue": "",
						"wen": "진료",
						"thr": "",
						"fir": "",
						"sat": "2주"
					},
					"afternoon": {
						"mon": "",
						"tue": "진료",
						"wen": "",
						"thr": "진료",
						"fir": "",
						"sat": "진료"
					},
					"other": {
						"first": "출장 : 2023-02-13~2023-02-14",
						"second": "출장 : 2023-02-15~2023-02-15"
					},
					"doctorImg": "황원민_교수"
				}
			],
			"type6": [
				{
					"idx": 0
				},
				{
					"idx": 1,
					"name": "김현우",
					"doctorField": "신부전, 당뇨병/고혈압성 신질환, 투석, 신장이식, 사구체신염",
					"career": [
						"가톨릭 중앙의료원 부속병원 인턴",
						"가톨릭 중앙의료원 부속병원 레지던트",
						"1992.4 ~ 1994.4국군수도통합병원 내과장",
						"1995.5 ~ 1996.2강남성모병원 내과 신장학 교실 임상강사",
						"1996.3 ~ 2000.1가톨릭의대 내과학 교실 전임강사",
						"건양대학교병원 교육연구부장 역임"
					],
					"morning": {
						"mon": "",
						"tue": "진료",
						"wen": "진료",
						"thr": "",
						"fir": "",
						"sat": "2주"
					},
					"afternoon": {
						"mon": "",
						"tue": "진료",
						"wen": "",
						"thr": "",
						"fir": "",
						"sat": "진료"
					},
					"other": {
						"first": "출장 : 2023-02-13~2023-02-14",
						"second": "출장 : 2023-02-15~2023-02-15"
					},
					"doctorImg": "윤성로_교수"
				},
				{
					"idx": 2,
					"name": "신의규",
					"doctorField": "혈뇨, 단백뇨, 부종, 만성신부전, 투석, 신장이식, 노인의학",
					"career": [
						"대전광역시 의사회 부회장",
						"EBS 명의 스페셜",
						"건양대학교병원 심사평가실장 역임",
						"현) 건양대학교병원 심사평가실장"
					],
					"morning": {
						"mon": "진료",
						"tue": "",
						"wen": "진료",
						"thr": "",
						"fir": "",
						"sat": "2주"
					},
					"afternoon": {
						"mon": "",
						"tue": "진료",
						"wen": "",
						"thr": "진료",
						"fir": "",
						"sat": "진료"
					},
					"other": {
						"first": "출장 : 2023-02-13~2023-02-14",
						"second": "출장 : 2023-02-15~2023-02-15"
					},
					"doctorImg": "황원민_교수"
				}
			],
			"type7": [
				{
					"idx": 0
				},
				{
					"idx": 1,
					"name": "김현우",
					"doctorField": "신부전, 당뇨병/고혈압성 신질환, 투석, 신장이식, 사구체신염",
					"career": [
						"가톨릭 중앙의료원 부속병원 인턴",
						"가톨릭 중앙의료원 부속병원 레지던트",
						"1992.4 ~ 1994.4국군수도통합병원 내과장",
						"1995.5 ~ 1996.2강남성모병원 내과 신장학 교실 임상강사",
						"1996.3 ~ 2000.1가톨릭의대 내과학 교실 전임강사",
						"건양대학교병원 교육연구부장 역임"
					],
					"morning": {
						"mon": "",
						"tue": "진료",
						"wen": "진료",
						"thr": "",
						"fir": "",
						"sat": "2주"
					},
					"afternoon": {
						"mon": "",
						"tue": "진료",
						"wen": "",
						"thr": "",
						"fir": "",
						"sat": "진료"
					},
					"other": {
						"first": "출장 : 2023-02-13~2023-02-14",
						"second": "출장 : 2023-02-15~2023-02-15"
					},
					"doctorImg": "윤성로_교수"
				},
				{
					"idx": 2,
					"name": "신의규",
					"doctorField": "혈뇨, 단백뇨, 부종, 만성신부전, 투석, 신장이식, 노인의학",
					"career": [
						"대전광역시 의사회 부회장",
						"EBS 명의 스페셜",
						"건양대학교병원 심사평가실장 역임",
						"현) 건양대학교병원 심사평가실장"
					],
					"morning": {
						"mon": "진료",
						"tue": "",
						"wen": "진료",
						"thr": "",
						"fir": "",
						"sat": "2주"
					},
					"afternoon": {
						"mon": "",
						"tue": "진료",
						"wen": "",
						"thr": "진료",
						"fir": "",
						"sat": "진료"
					},
					"other": {
						"first": "출장 : 2023-02-13~2023-02-14",
						"second": "출장 : 2023-02-15~2023-02-15"
					},
					"doctorImg": "황원민_교수"
				}
			],
			"type8": [
				{
					"idx": 0
				},
				{
					"idx": 1,
					"name": "김현우",
					"doctorField": "신부전, 당뇨병/고혈압성 신질환, 투석, 신장이식, 사구체신염",
					"career": [
						"가톨릭 중앙의료원 부속병원 인턴",
						"가톨릭 중앙의료원 부속병원 레지던트",
						"1992.4 ~ 1994.4국군수도통합병원 내과장",
						"1995.5 ~ 1996.2강남성모병원 내과 신장학 교실 임상강사",
						"1996.3 ~ 2000.1가톨릭의대 내과학 교실 전임강사",
						"건양대학교병원 교육연구부장 역임"
					],
					"morning": {
						"mon": "",
						"tue": "진료",
						"wen": "진료",
						"thr": "",
						"fir": "",
						"sat": "2주"
					},
					"afternoon": {
						"mon": "",
						"tue": "진료",
						"wen": "",
						"thr": "",
						"fir": "",
						"sat": "진료"
					},
					"other": {
						"first": "출장 : 2023-02-13~2023-02-14",
						"second": "출장 : 2023-02-15~2023-02-15"
					},
					"doctorImg": "윤성로_교수"
				},
				{
					"idx": 2,
					"name": "신의규",
					"doctorField": "혈뇨, 단백뇨, 부종, 만성신부전, 투석, 신장이식, 노인의학",
					"career": [
						"대전광역시 의사회 부회장",
						"EBS 명의 스페셜",
						"건양대학교병원 심사평가실장 역임",
						"현) 건양대학교병원 심사평가실장"
					],
					"morning": {
						"mon": "진료",
						"tue": "",
						"wen": "진료",
						"thr": "",
						"fir": "",
						"sat": "2주"
					},
					"afternoon": {
						"mon": "",
						"tue": "진료",
						"wen": "",
						"thr": "진료",
						"fir": "",
						"sat": "진료"
					},
					"other": {
						"first": "출장 : 2023-02-13~2023-02-14",
						"second": "출장 : 2023-02-15~2023-02-15"
					},
					"doctorImg": "황원민_교수"
				}
			],
			"type9": [
				{
					"idx": 0
				},
				{
					"idx": 1,
					"name": "김현우",
					"doctorField": "신부전, 당뇨병/고혈압성 신질환, 투석, 신장이식, 사구체신염",
					"career": [
						"가톨릭 중앙의료원 부속병원 인턴",
						"가톨릭 중앙의료원 부속병원 레지던트",
						"1992.4 ~ 1994.4국군수도통합병원 내과장",
						"1995.5 ~ 1996.2강남성모병원 내과 신장학 교실 임상강사",
						"1996.3 ~ 2000.1가톨릭의대 내과학 교실 전임강사",
						"건양대학교병원 교육연구부장 역임"
					],
					"morning": {
						"mon": "",
						"tue": "진료",
						"wen": "진료",
						"thr": "",
						"fir": "",
						"sat": "2주"
					},
					"afternoon": {
						"mon": "",
						"tue": "진료",
						"wen": "",
						"thr": "",
						"fir": "",
						"sat": "진료"
					},
					"other": {
						"first": "출장 : 2023-02-13~2023-02-14",
						"second": "출장 : 2023-02-15~2023-02-15"
					},
					"doctorImg": "윤성로_교수"
				},
				{
					"idx": 2,
					"name": "신의규",
					"doctorField": "혈뇨, 단백뇨, 부종, 만성신부전, 투석, 신장이식, 노인의학",
					"career": [
						"대전광역시 의사회 부회장",
						"EBS 명의 스페셜",
						"건양대학교병원 심사평가실장 역임",
						"현) 건양대학교병원 심사평가실장"
					],
					"morning": {
						"mon": "진료",
						"tue": "",
						"wen": "진료",
						"thr": "",
						"fir": "",
						"sat": "2주"
					},
					"afternoon": {
						"mon": "",
						"tue": "진료",
						"wen": "",
						"thr": "진료",
						"fir": "",
						"sat": "진료"
					},
					"other": {
						"first": "출장 : 2023-02-13~2023-02-14",
						"second": "출장 : 2023-02-15~2023-02-15"
					},
					"doctorImg": "황원민_교수"
				}
			],
			"type10": [
				{
					"idx": 0
				},
				{
					"idx": 1,
					"name": "김현우",
					"doctorField": "신부전, 당뇨병/고혈압성 신질환, 투석, 신장이식, 사구체신염",
					"career": [
						"가톨릭 중앙의료원 부속병원 인턴",
						"가톨릭 중앙의료원 부속병원 레지던트",
						"1992.4 ~ 1994.4국군수도통합병원 내과장",
						"1995.5 ~ 1996.2강남성모병원 내과 신장학 교실 임상강사",
						"1996.3 ~ 2000.1가톨릭의대 내과학 교실 전임강사",
						"건양대학교병원 교육연구부장 역임"
					],
					"morning": {
						"mon": "",
						"tue": "진료",
						"wen": "진료",
						"thr": "",
						"fir": "",
						"sat": "2주"
					},
					"afternoon": {
						"mon": "",
						"tue": "진료",
						"wen": "",
						"thr": "",
						"fir": "",
						"sat": "진료"
					},
					"other": {
						"first": "출장 : 2023-02-13~2023-02-14",
						"second": "출장 : 2023-02-15~2023-02-15"
					},
					"doctorImg": "윤성로_교수"
				},
				{
					"idx": 2,
					"name": "신의규",
					"doctorField": "혈뇨, 단백뇨, 부종, 만성신부전, 투석, 신장이식, 노인의학",
					"career": [
						"대전광역시 의사회 부회장",
						"EBS 명의 스페셜",
						"건양대학교병원 심사평가실장 역임",
						"현) 건양대학교병원 심사평가실장"
					],
					"morning": {
						"mon": "진료",
						"tue": "",
						"wen": "진료",
						"thr": "",
						"fir": "",
						"sat": "2주"
					},
					"afternoon": {
						"mon": "",
						"tue": "진료",
						"wen": "",
						"thr": "진료",
						"fir": "",
						"sat": "진료"
					},
					"other": {
						"first": "출장 : 2023-02-13~2023-02-14",
						"second": "출장 : 2023-02-15~2023-02-15"
					},
					"doctorImg": "황원민_교수"
				}
			],
			"type11": [
				{
					"idx": 0
				},
				{
					"idx": 1,
					"name": "김현우",
					"doctorField": "신부전, 당뇨병/고혈압성 신질환, 투석, 신장이식, 사구체신염",
					"career": [
						"가톨릭 중앙의료원 부속병원 인턴",
						"가톨릭 중앙의료원 부속병원 레지던트",
						"1992.4 ~ 1994.4국군수도통합병원 내과장",
						"1995.5 ~ 1996.2강남성모병원 내과 신장학 교실 임상강사",
						"1996.3 ~ 2000.1가톨릭의대 내과학 교실 전임강사",
						"건양대학교병원 교육연구부장 역임"
					],
					"morning": {
						"mon": "",
						"tue": "진료",
						"wen": "진료",
						"thr": "",
						"fir": "",
						"sat": "2주"
					},
					"afternoon": {
						"mon": "",
						"tue": "진료",
						"wen": "",
						"thr": "",
						"fir": "",
						"sat": "진료"
					},
					"other": {
						"first": "출장 : 2023-02-13~2023-02-14",
						"second": "출장 : 2023-02-15~2023-02-15"
					},
					"doctorImg": "윤성로_교수"
				},
				{
					"idx": 2,
					"name": "신의규",
					"doctorField": "혈뇨, 단백뇨, 부종, 만성신부전, 투석, 신장이식, 노인의학",
					"career": [
						"대전광역시 의사회 부회장",
						"EBS 명의 스페셜",
						"건양대학교병원 심사평가실장 역임",
						"현) 건양대학교병원 심사평가실장"
					],
					"morning": {
						"mon": "진료",
						"tue": "",
						"wen": "진료",
						"thr": "",
						"fir": "",
						"sat": "2주"
					},
					"afternoon": {
						"mon": "",
						"tue": "진료",
						"wen": "",
						"thr": "진료",
						"fir": "",
						"sat": "진료"
					},
					"other": {
						"first": "출장 : 2023-02-13~2023-02-14",
						"second": "출장 : 2023-02-15~2023-02-15"
					},
					"doctorImg": "황원민_교수"
				},
				{
					"idx": 3,
					"name": "박재성",
					"doctorField": "혈뇨, 단백뇨, 부종, 만성신부전, 투석, 신장이식, 노인의학",
					"career": [
						"대전광역시 의사회 부회장",
						"EBS 명의 스페셜",
						"건양대학교병원 심사평가실장 역임",
						"현) 건양대학교병원 심사평가실장"
					],
					"morning": {
						"mon": "진료",
						"tue": "",
						"wen": "진료",
						"thr": "",
						"fir": "",
						"sat": "2주"
					},
					"afternoon": {
						"mon": "",
						"tue": "진료",
						"wen": "",
						"thr": "진료",
						"fir": "",
						"sat": "진료"
					},
					"other": {
						"first": "출장 : 2023-02-13~2023-02-14",
						"second": "출장 : 2023-02-15~2023-02-15"
					},
					"doctorImg": "윤세희_교수"
				},
				{
					"idx": 4,
					"name": "문재곤",
					"doctorField": "혈뇨, 단백뇨, 부종, 만성신부전, 투석, 신장이식, 노인의학",
					"career": [
						"대전광역시 의사회 부회장",
						"EBS 명의 스페셜",
						"건양대학교병원 심사평가실장 역임",
						"현) 건양대학교병원 심사평가실장"
					],
					"morning": {
						"mon": "진료",
						"tue": "",
						"wen": "진료",
						"thr": "",
						"fir": "",
						"sat": "2주"
					},
					"afternoon": {
						"mon": "",
						"tue": "진료",
						"wen": "",
						"thr": "진료",
						"fir": "",
						"sat": "진료"
					},
					"other": {
						"first": "출장 : 2023-02-13~2023-02-14",
						"second": "출장 : 2023-02-15~2023-02-15"
					},
					"doctorImg": "박요한_교수"
				},
				{
					"idx": 5,
					"name": "주진양",
					"doctorField": "혈뇨, 단백뇨, 부종, 만성신부전, 투석, 신장이식, 노인의학",
					"career": [
						"대전광역시 의사회 부회장",
						"EBS 명의 스페셜",
						"건양대학교병원 심사평가실장 역임",
						"현) 건양대학교병원 심사평가실장"
					],
					"morning": {
						"mon": "진료",
						"tue": "",
						"wen": "진료",
						"thr": "",
						"fir": "",
						"sat": "2주"
					},
					"afternoon": {
						"mon": "",
						"tue": "진료",
						"wen": "",
						"thr": "진료",
						"fir": "",
						"sat": "진료"
					},
					"other": {
						"first": "출장 : 2023-02-13~2023-02-14",
						"second": "출장 : 2023-02-15~2023-02-15"
					},
					"doctorImg": "박성지_교수"
				},
				{
					"idx": 6,
					"name": "서인엽",
					"doctorField": "혈뇨, 단백뇨, 부종, 만성신부전, 투석, 신장이식, 노인의학",
					"career": [
						"대전광역시 의사회 부회장",
						"EBS 명의 스페셜",
						"건양대학교병원 심사평가실장 역임",
						"현) 건양대학교병원 심사평가실장"
					],
					"morning": {
						"mon": "진료",
						"tue": "",
						"wen": "진료",
						"thr": "",
						"fir": "",
						"sat": "2주"
					},
					"afternoon": {
						"mon": "",
						"tue": "진료",
						"wen": "",
						"thr": "진료",
						"fir": "",
						"sat": "진료"
					},
					"other": {
						"first": "출장 : 2023-02-13~2023-02-14",
						"second": "출장 : 2023-02-15~2023-02-15"
					},
					"doctorImg": "박성지_교수"
				}
			],
			"type12": [
				{
					"idx": 0
				},
				{
					"idx": 1,
					"name": "김현우",
					"doctorField": "신부전, 당뇨병/고혈압성 신질환, 투석, 신장이식, 사구체신염",
					"career": [
						"가톨릭 중앙의료원 부속병원 인턴",
						"가톨릭 중앙의료원 부속병원 레지던트",
						"1992.4 ~ 1994.4국군수도통합병원 내과장",
						"1995.5 ~ 1996.2강남성모병원 내과 신장학 교실 임상강사",
						"1996.3 ~ 2000.1가톨릭의대 내과학 교실 전임강사",
						"건양대학교병원 교육연구부장 역임"
					],
					"morning": {
						"mon": "",
						"tue": "진료",
						"wen": "진료",
						"thr": "",
						"fir": "",
						"sat": "2주"
					},
					"afternoon": {
						"mon": "",
						"tue": "진료",
						"wen": "",
						"thr": "",
						"fir": "",
						"sat": "진료"
					},
					"other": {
						"first": "출장 : 2023-02-13~2023-02-14",
						"second": "출장 : 2023-02-15~2023-02-15"
					},
					"doctorImg": "윤성로_교수"
				},
				{
					"idx": 2,
					"name": "신의규",
					"doctorField": "혈뇨, 단백뇨, 부종, 만성신부전, 투석, 신장이식, 노인의학",
					"career": [
						"대전광역시 의사회 부회장",
						"EBS 명의 스페셜",
						"건양대학교병원 심사평가실장 역임",
						"현) 건양대학교병원 심사평가실장"
					],
					"morning": {
						"mon": "진료",
						"tue": "",
						"wen": "진료",
						"thr": "",
						"fir": "",
						"sat": "2주"
					},
					"afternoon": {
						"mon": "",
						"tue": "진료",
						"wen": "",
						"thr": "진료",
						"fir": "",
						"sat": "진료"
					},
					"other": {
						"first": "출장 : 2023-02-13~2023-02-14",
						"second": "출장 : 2023-02-15~2023-02-15"
					},
					"doctorImg": "황원민_교수"
				}
			],
			"type13": [
				{
					"idx": 0
				},
				{
					"idx": 1,
					"name": "김현우",
					"doctorField": "신부전, 당뇨병/고혈압성 신질환, 투석, 신장이식, 사구체신염",
					"career": [
						"가톨릭 중앙의료원 부속병원 인턴",
						"가톨릭 중앙의료원 부속병원 레지던트",
						"1992.4 ~ 1994.4국군수도통합병원 내과장",
						"1995.5 ~ 1996.2강남성모병원 내과 신장학 교실 임상강사",
						"1996.3 ~ 2000.1가톨릭의대 내과학 교실 전임강사",
						"건양대학교병원 교육연구부장 역임"
					],
					"morning": {
						"mon": "",
						"tue": "진료",
						"wen": "진료",
						"thr": "",
						"fir": "",
						"sat": "2주"
					},
					"afternoon": {
						"mon": "",
						"tue": "진료",
						"wen": "",
						"thr": "",
						"fir": "",
						"sat": "진료"
					},
					"other": {
						"first": "출장 : 2023-02-13~2023-02-14",
						"second": "출장 : 2023-02-15~2023-02-15"
					},
					"doctorImg": "윤성로_교수"
				},
				{
					"idx": 2,
					"name": "신의규",
					"doctorField": "혈뇨, 단백뇨, 부종, 만성신부전, 투석, 신장이식, 노인의학",
					"career": [
						"대전광역시 의사회 부회장",
						"EBS 명의 스페셜",
						"건양대학교병원 심사평가실장 역임",
						"현) 건양대학교병원 심사평가실장"
					],
					"morning": {
						"mon": "진료",
						"tue": "",
						"wen": "진료",
						"thr": "",
						"fir": "",
						"sat": "2주"
					},
					"afternoon": {
						"mon": "",
						"tue": "진료",
						"wen": "",
						"thr": "진료",
						"fir": "",
						"sat": "진료"
					},
					"other": {
						"first": "출장 : 2023-02-13~2023-02-14",
						"second": "출장 : 2023-02-15~2023-02-15"
					},
					"doctorImg": "황원민_교수"
				}
			],
			"type14": [
				{
					"idx": 0
				},
				{
					"idx": 1,
					"name": "김현우",
					"doctorField": "신부전, 당뇨병/고혈압성 신질환, 투석, 신장이식, 사구체신염",
					"career": [
						"가톨릭 중앙의료원 부속병원 인턴",
						"가톨릭 중앙의료원 부속병원 레지던트",
						"1992.4 ~ 1994.4국군수도통합병원 내과장",
						"1995.5 ~ 1996.2강남성모병원 내과 신장학 교실 임상강사",
						"1996.3 ~ 2000.1가톨릭의대 내과학 교실 전임강사",
						"건양대학교병원 교육연구부장 역임"
					],
					"morning": {
						"mon": "",
						"tue": "진료",
						"wen": "진료",
						"thr": "",
						"fir": "",
						"sat": "2주"
					},
					"afternoon": {
						"mon": "",
						"tue": "진료",
						"wen": "",
						"thr": "",
						"fir": "",
						"sat": "진료"
					},
					"other": {
						"first": "출장 : 2023-02-13~2023-02-14",
						"second": "출장 : 2023-02-15~2023-02-15"
					},
					"doctorImg": "윤성로_교수"
				},
				{
					"idx": 2,
					"name": "신의규",
					"doctorField": "혈뇨, 단백뇨, 부종, 만성신부전, 투석, 신장이식, 노인의학",
					"career": [
						"대전광역시 의사회 부회장",
						"EBS 명의 스페셜",
						"건양대학교병원 심사평가실장 역임",
						"현) 건양대학교병원 심사평가실장"
					],
					"morning": {
						"mon": "진료",
						"tue": "",
						"wen": "진료",
						"thr": "",
						"fir": "",
						"sat": "2주"
					},
					"afternoon": {
						"mon": "",
						"tue": "진료",
						"wen": "",
						"thr": "진료",
						"fir": "",
						"sat": "진료"
					},
					"other": {
						"first": "출장 : 2023-02-13~2023-02-14",
						"second": "출장 : 2023-02-15~2023-02-15"
					},
					"doctorImg": "황원민_교수"
				}
			],
			"type15": [
				{
					"idx": 0
				},
				{
					"idx": 1,
					"name": "김현우",
					"doctorField": "신부전, 당뇨병/고혈압성 신질환, 투석, 신장이식, 사구체신염",
					"career": [
						"가톨릭 중앙의료원 부속병원 인턴",
						"가톨릭 중앙의료원 부속병원 레지던트",
						"1992.4 ~ 1994.4국군수도통합병원 내과장",
						"1995.5 ~ 1996.2강남성모병원 내과 신장학 교실 임상강사",
						"1996.3 ~ 2000.1가톨릭의대 내과학 교실 전임강사",
						"건양대학교병원 교육연구부장 역임"
					],
					"morning": {
						"mon": "",
						"tue": "진료",
						"wen": "진료",
						"thr": "",
						"fir": "",
						"sat": "2주"
					},
					"afternoon": {
						"mon": "",
						"tue": "진료",
						"wen": "",
						"thr": "",
						"fir": "",
						"sat": "진료"
					},
					"other": {
						"first": "출장 : 2023-02-13~2023-02-14",
						"second": "출장 : 2023-02-15~2023-02-15"
					},
					"doctorImg": "윤성로_교수"
				},
				{
					"idx": 2,
					"name": "신의규",
					"doctorField": "혈뇨, 단백뇨, 부종, 만성신부전, 투석, 신장이식, 노인의학",
					"career": [
						"대전광역시 의사회 부회장",
						"EBS 명의 스페셜",
						"건양대학교병원 심사평가실장 역임",
						"현) 건양대학교병원 심사평가실장"
					],
					"morning": {
						"mon": "진료",
						"tue": "",
						"wen": "진료",
						"thr": "",
						"fir": "",
						"sat": "2주"
					},
					"afternoon": {
						"mon": "",
						"tue": "진료",
						"wen": "",
						"thr": "진료",
						"fir": "",
						"sat": "진료"
					},
					"other": {
						"first": "출장 : 2023-02-13~2023-02-14",
						"second": "출장 : 2023-02-15~2023-02-15"
					},
					"doctorImg": "황원민_교수"
				}
			],
			"type16": [
				{
					"idx": 0
				},
				{
					"idx": 1,
					"name": "김현우",
					"doctorField": "신부전, 당뇨병/고혈압성 신질환, 투석, 신장이식, 사구체신염",
					"career": [
						"가톨릭 중앙의료원 부속병원 인턴",
						"가톨릭 중앙의료원 부속병원 레지던트",
						"1992.4 ~ 1994.4국군수도통합병원 내과장",
						"1995.5 ~ 1996.2강남성모병원 내과 신장학 교실 임상강사",
						"1996.3 ~ 2000.1가톨릭의대 내과학 교실 전임강사",
						"건양대학교병원 교육연구부장 역임"
					],
					"morning": {
						"mon": "",
						"tue": "진료",
						"wen": "진료",
						"thr": "",
						"fir": "",
						"sat": "2주"
					},
					"afternoon": {
						"mon": "",
						"tue": "진료",
						"wen": "",
						"thr": "",
						"fir": "",
						"sat": "진료"
					},
					"other": {
						"first": "출장 : 2023-02-13~2023-02-14",
						"second": "출장 : 2023-02-15~2023-02-15"
					},
					"doctorImg": "윤성로_교수"
				},
				{
					"idx": 2,
					"name": "신의규",
					"doctorField": "혈뇨, 단백뇨, 부종, 만성신부전, 투석, 신장이식, 노인의학",
					"career": [
						"대전광역시 의사회 부회장",
						"EBS 명의 스페셜",
						"건양대학교병원 심사평가실장 역임",
						"현) 건양대학교병원 심사평가실장"
					],
					"morning": {
						"mon": "진료",
						"tue": "",
						"wen": "진료",
						"thr": "",
						"fir": "",
						"sat": "2주"
					},
					"afternoon": {
						"mon": "",
						"tue": "진료",
						"wen": "",
						"thr": "진료",
						"fir": "",
						"sat": "진료"
					},
					"other": {
						"first": "출장 : 2023-02-13~2023-02-14",
						"second": "출장 : 2023-02-15~2023-02-15"
					},
					"doctorImg": "황원민_교수"
				}
			],
			"type17": [
				{
					"idx": 0
				},
				{
					"idx": 1,
					"name": "김현우",
					"doctorField": "신부전, 당뇨병/고혈압성 신질환, 투석, 신장이식, 사구체신염",
					"career": [
						"가톨릭 중앙의료원 부속병원 인턴",
						"가톨릭 중앙의료원 부속병원 레지던트",
						"1992.4 ~ 1994.4국군수도통합병원 내과장",
						"1995.5 ~ 1996.2강남성모병원 내과 신장학 교실 임상강사",
						"1996.3 ~ 2000.1가톨릭의대 내과학 교실 전임강사",
						"건양대학교병원 교육연구부장 역임"
					],
					"morning": {
						"mon": "",
						"tue": "진료",
						"wen": "진료",
						"thr": "",
						"fir": "",
						"sat": "2주"
					},
					"afternoon": {
						"mon": "",
						"tue": "진료",
						"wen": "",
						"thr": "",
						"fir": "",
						"sat": "진료"
					},
					"other": {
						"first": "출장 : 2023-02-13~2023-02-14",
						"second": "출장 : 2023-02-15~2023-02-15"
					},
					"doctorImg": "윤성로_교수"
				},
				{
					"idx": 2,
					"name": "신의규",
					"doctorField": "혈뇨, 단백뇨, 부종, 만성신부전, 투석, 신장이식, 노인의학",
					"career": [
						"대전광역시 의사회 부회장",
						"EBS 명의 스페셜",
						"건양대학교병원 심사평가실장 역임",
						"현) 건양대학교병원 심사평가실장"
					],
					"morning": {
						"mon": "진료",
						"tue": "",
						"wen": "진료",
						"thr": "",
						"fir": "",
						"sat": "2주"
					},
					"afternoon": {
						"mon": "",
						"tue": "진료",
						"wen": "",
						"thr": "진료",
						"fir": "",
						"sat": "진료"
					},
					"other": {
						"first": "출장 : 2023-02-13~2023-02-14",
						"second": "출장 : 2023-02-15~2023-02-15"
					},
					"doctorImg": "황원민_교수"
				}
			],
			"type18": [
				{
					"idx": 0
				},
				{
					"idx": 1,
					"name": "김현우",
					"doctorField": "신부전, 당뇨병/고혈압성 신질환, 투석, 신장이식, 사구체신염",
					"career": [
						"가톨릭 중앙의료원 부속병원 인턴",
						"가톨릭 중앙의료원 부속병원 레지던트",
						"1992.4 ~ 1994.4국군수도통합병원 내과장",
						"1995.5 ~ 1996.2강남성모병원 내과 신장학 교실 임상강사",
						"1996.3 ~ 2000.1가톨릭의대 내과학 교실 전임강사",
						"건양대학교병원 교육연구부장 역임"
					],
					"morning": {
						"mon": "",
						"tue": "진료",
						"wen": "진료",
						"thr": "",
						"fir": "",
						"sat": "2주"
					},
					"afternoon": {
						"mon": "",
						"tue": "진료",
						"wen": "",
						"thr": "",
						"fir": "",
						"sat": "진료"
					},
					"other": {
						"first": "출장 : 2023-02-13~2023-02-14",
						"second": "출장 : 2023-02-15~2023-02-15"
					},
					"doctorImg": "윤성로_교수"
				},
				{
					"idx": 2,
					"name": "신의규",
					"doctorField": "혈뇨, 단백뇨, 부종, 만성신부전, 투석, 신장이식, 노인의학",
					"career": [
						"대전광역시 의사회 부회장",
						"EBS 명의 스페셜",
						"건양대학교병원 심사평가실장 역임",
						"현) 건양대학교병원 심사평가실장"
					],
					"morning": {
						"mon": "진료",
						"tue": "",
						"wen": "진료",
						"thr": "",
						"fir": "",
						"sat": "2주"
					},
					"afternoon": {
						"mon": "",
						"tue": "진료",
						"wen": "",
						"thr": "진료",
						"fir": "",
						"sat": "진료"
					},
					"other": {
						"first": "출장 : 2023-02-13~2023-02-14",
						"second": "출장 : 2023-02-15~2023-02-15"
					},
					"doctorImg": "황원민_교수"
				}
			],
			"type19": [
				{
					"idx": 0
				},
				{
					"idx": 1,
					"name": "김현우",
					"doctorField": "신부전, 당뇨병/고혈압성 신질환, 투석, 신장이식, 사구체신염",
					"career": [
						"가톨릭 중앙의료원 부속병원 인턴",
						"가톨릭 중앙의료원 부속병원 레지던트",
						"1992.4 ~ 1994.4국군수도통합병원 내과장",
						"1995.5 ~ 1996.2강남성모병원 내과 신장학 교실 임상강사",
						"1996.3 ~ 2000.1가톨릭의대 내과학 교실 전임강사",
						"건양대학교병원 교육연구부장 역임"
					],
					"morning": {
						"mon": "",
						"tue": "진료",
						"wen": "진료",
						"thr": "",
						"fir": "",
						"sat": "2주"
					},
					"afternoon": {
						"mon": "",
						"tue": "진료",
						"wen": "",
						"thr": "",
						"fir": "",
						"sat": "진료"
					},
					"other": {
						"first": "출장 : 2023-02-13~2023-02-14",
						"second": "출장 : 2023-02-15~2023-02-15"
					},
					"doctorImg": "윤성로_교수"
				},
				{
					"idx": 2,
					"name": "신의규",
					"doctorField": "혈뇨, 단백뇨, 부종, 만성신부전, 투석, 신장이식, 노인의학",
					"career": [
						"대전광역시 의사회 부회장",
						"EBS 명의 스페셜",
						"건양대학교병원 심사평가실장 역임",
						"현) 건양대학교병원 심사평가실장"
					],
					"morning": {
						"mon": "진료",
						"tue": "",
						"wen": "진료",
						"thr": "",
						"fir": "",
						"sat": "2주"
					},
					"afternoon": {
						"mon": "",
						"tue": "진료",
						"wen": "",
						"thr": "진료",
						"fir": "",
						"sat": "진료"
					},
					"other": {
						"first": "출장 : 2023-02-13~2023-02-14",
						"second": "출장 : 2023-02-15~2023-02-15"
					},
					"doctorImg": "황원민_교수"
				}
			],
			"type20": [
				{
					"idx": 0
				},
				{
					"idx": 1,
					"name": "김현우",
					"doctorField": "신부전, 당뇨병/고혈압성 신질환, 투석, 신장이식, 사구체신염",
					"career": [
						"가톨릭 중앙의료원 부속병원 인턴",
						"가톨릭 중앙의료원 부속병원 레지던트",
						"1992.4 ~ 1994.4국군수도통합병원 내과장",
						"1995.5 ~ 1996.2강남성모병원 내과 신장학 교실 임상강사",
						"1996.3 ~ 2000.1가톨릭의대 내과학 교실 전임강사",
						"건양대학교병원 교육연구부장 역임"
					],
					"morning": {
						"mon": "",
						"tue": "진료",
						"wen": "진료",
						"thr": "",
						"fir": "",
						"sat": "2주"
					},
					"afternoon": {
						"mon": "",
						"tue": "진료",
						"wen": "",
						"thr": "",
						"fir": "",
						"sat": "진료"
					},
					"other": {
						"first": "출장 : 2023-02-13~2023-02-14",
						"second": "출장 : 2023-02-15~2023-02-15"
					},
					"doctorImg": "윤성로_교수"
				},
				{
					"idx": 2,
					"name": "신의규",
					"doctorField": "혈뇨, 단백뇨, 부종, 만성신부전, 투석, 신장이식, 노인의학",
					"career": [
						"대전광역시 의사회 부회장",
						"EBS 명의 스페셜",
						"건양대학교병원 심사평가실장 역임",
						"현) 건양대학교병원 심사평가실장"
					],
					"morning": {
						"mon": "진료",
						"tue": "",
						"wen": "진료",
						"thr": "",
						"fir": "",
						"sat": "2주"
					},
					"afternoon": {
						"mon": "",
						"tue": "진료",
						"wen": "",
						"thr": "진료",
						"fir": "",
						"sat": "진료"
					},
					"other": {
						"first": "출장 : 2023-02-13~2023-02-14",
						"second": "출장 : 2023-02-15~2023-02-15"
					},
					"doctorImg": "황원민_교수"
				}
			],
			"type21": [
				{
					"idx": 0
				},
				{
					"idx": 1,
					"name": "김현우",
					"doctorField": "신부전, 당뇨병/고혈압성 신질환, 투석, 신장이식, 사구체신염",
					"career": [
						"가톨릭 중앙의료원 부속병원 인턴",
						"가톨릭 중앙의료원 부속병원 레지던트",
						"1992.4 ~ 1994.4국군수도통합병원 내과장",
						"1995.5 ~ 1996.2강남성모병원 내과 신장학 교실 임상강사",
						"1996.3 ~ 2000.1가톨릭의대 내과학 교실 전임강사",
						"건양대학교병원 교육연구부장 역임"
					],
					"morning": {
						"mon": "",
						"tue": "진료",
						"wen": "진료",
						"thr": "",
						"fir": "",
						"sat": "2주"
					},
					"afternoon": {
						"mon": "",
						"tue": "진료",
						"wen": "",
						"thr": "",
						"fir": "",
						"sat": "진료"
					},
					"other": {
						"first": "출장 : 2023-02-13~2023-02-14",
						"second": "출장 : 2023-02-15~2023-02-15"
					},
					"doctorImg": "윤성로_교수"
				},
				{
					"idx": 2,
					"name": "신의규",
					"doctorField": "혈뇨, 단백뇨, 부종, 만성신부전, 투석, 신장이식, 노인의학",
					"career": [
						"대전광역시 의사회 부회장",
						"EBS 명의 스페셜",
						"건양대학교병원 심사평가실장 역임",
						"현) 건양대학교병원 심사평가실장"
					],
					"morning": {
						"mon": "진료",
						"tue": "",
						"wen": "진료",
						"thr": "",
						"fir": "",
						"sat": "2주"
					},
					"afternoon": {
						"mon": "",
						"tue": "진료",
						"wen": "",
						"thr": "진료",
						"fir": "",
						"sat": "진료"
					},
					"other": {
						"first": "출장 : 2023-02-13~2023-02-14",
						"second": "출장 : 2023-02-15~2023-02-15"
					},
					"doctorImg": "황원민_교수"
				}
			],
			"type22": [
				{
					"idx": 0
				},
				{
					"idx": 1,
					"name": "김현우",
					"doctorField": "신부전, 당뇨병/고혈압성 신질환, 투석, 신장이식, 사구체신염",
					"career": [
						"가톨릭 중앙의료원 부속병원 인턴",
						"가톨릭 중앙의료원 부속병원 레지던트",
						"1992.4 ~ 1994.4국군수도통합병원 내과장",
						"1995.5 ~ 1996.2강남성모병원 내과 신장학 교실 임상강사",
						"1996.3 ~ 2000.1가톨릭의대 내과학 교실 전임강사",
						"건양대학교병원 교육연구부장 역임"
					],
					"morning": {
						"mon": "",
						"tue": "진료",
						"wen": "진료",
						"thr": "",
						"fir": "",
						"sat": "2주"
					},
					"afternoon": {
						"mon": "",
						"tue": "진료",
						"wen": "",
						"thr": "",
						"fir": "",
						"sat": "진료"
					},
					"other": {
						"first": "출장 : 2023-02-13~2023-02-14",
						"second": "출장 : 2023-02-15~2023-02-15"
					},
					"doctorImg": "윤성로_교수"
				},
				{
					"idx": 2,
					"name": "신의규",
					"doctorField": "혈뇨, 단백뇨, 부종, 만성신부전, 투석, 신장이식, 노인의학",
					"career": [
						"대전광역시 의사회 부회장",
						"EBS 명의 스페셜",
						"건양대학교병원 심사평가실장 역임",
						"현) 건양대학교병원 심사평가실장"
					],
					"morning": {
						"mon": "진료",
						"tue": "",
						"wen": "진료",
						"thr": "",
						"fir": "",
						"sat": "2주"
					},
					"afternoon": {
						"mon": "",
						"tue": "진료",
						"wen": "",
						"thr": "진료",
						"fir": "",
						"sat": "진료"
					},
					"other": {
						"first": "출장 : 2023-02-13~2023-02-14",
						"second": "출장 : 2023-02-15~2023-02-15"
					},
					"doctorImg": "황원민_교수"
				}
			],
			"type23": [
				{
					"idx": 0
				},
				{
					"idx": 1,
					"name": "김현우",
					"doctorField": "신부전, 당뇨병/고혈압성 신질환, 투석, 신장이식, 사구체신염",
					"career": [
						"가톨릭 중앙의료원 부속병원 인턴",
						"가톨릭 중앙의료원 부속병원 레지던트",
						"1992.4 ~ 1994.4국군수도통합병원 내과장",
						"1995.5 ~ 1996.2강남성모병원 내과 신장학 교실 임상강사",
						"1996.3 ~ 2000.1가톨릭의대 내과학 교실 전임강사",
						"건양대학교병원 교육연구부장 역임"
					],
					"morning": {
						"mon": "",
						"tue": "진료",
						"wen": "진료",
						"thr": "",
						"fir": "",
						"sat": "2주"
					},
					"afternoon": {
						"mon": "",
						"tue": "진료",
						"wen": "",
						"thr": "",
						"fir": "",
						"sat": "진료"
					},
					"other": {
						"first": "출장 : 2023-02-13~2023-02-14",
						"second": "출장 : 2023-02-15~2023-02-15"
					},
					"doctorImg": "윤성로_교수"
				},
				{
					"idx": 2,
					"name": "신의규",
					"doctorField": "혈뇨, 단백뇨, 부종, 만성신부전, 투석, 신장이식, 노인의학",
					"career": [
						"대전광역시 의사회 부회장",
						"EBS 명의 스페셜",
						"건양대학교병원 심사평가실장 역임",
						"현) 건양대학교병원 심사평가실장"
					],
					"morning": {
						"mon": "진료",
						"tue": "",
						"wen": "진료",
						"thr": "",
						"fir": "",
						"sat": "2주"
					},
					"afternoon": {
						"mon": "",
						"tue": "진료",
						"wen": "",
						"thr": "진료",
						"fir": "",
						"sat": "진료"
					},
					"other": {
						"first": "출장 : 2023-02-13~2023-02-14",
						"second": "출장 : 2023-02-15~2023-02-15"
					},
					"doctorImg": "황원민_교수"
				}
			]
		}